rust_ext/__init__.py
rust_ext-0.1.dist-info/DESCRIPTION.rst
rust_ext-0.1.dist-info/METADATA
rust_ext-0.1.dist-info/RECORD
rust_ext-0.1.dist-info/WHEEL
rust_ext-0.1.dist-info/metadata.json
rust_ext-0.1.dist-info/pbr.json
rust_ext-0.1.dist-info/top_level.txt
