Metadata-Version: 2.0
Name: rust-ext
Version: 0.1
Summary: Distutils helpers for rust Python extensions
Home-page: UNKNOWN
Author: James Salter
Author-email: iteration@gmail.com
License: MIT
Keywords: rust python extensions
Platform: UNKNOWN
